pystrat/__init__.py
pystrat/pystrat.py
pystrat/annotations/black shale.png
pystrat/annotations/climbing ripples.png
pystrat/annotations/convolute.png
pystrat/annotations/current.png
pystrat/annotations/dropstone.png
pystrat/annotations/geochron.png
pystrat/annotations/hcs.png
pystrat/annotations/microbial.png
pystrat/annotations/mudcrack.png
pystrat/annotations/nodule.png
pystrat/annotations/oolite.png
pystrat/annotations/pillow.png
pystrat/annotations/slump.png
pystrat/annotations/stromatolite.png
pystrat/annotations/swaley.png
pystrat/annotations/trough.png
pystrat/annotations/wave ripples.png
pystrat/swatches/601.png
pystrat/swatches/602.png
pystrat/swatches/603.png
pystrat/swatches/605.png
pystrat/swatches/606.png
pystrat/swatches/607.png
pystrat/swatches/608.png
pystrat/swatches/609.png
pystrat/swatches/610.png
pystrat/swatches/611.png
pystrat/swatches/612.png
pystrat/swatches/613.png
pystrat/swatches/614.png
pystrat/swatches/616.png
pystrat/swatches/617.png
pystrat/swatches/618.png
pystrat/swatches/619.png
pystrat/swatches/620.png
pystrat/swatches/621.png
pystrat/swatches/622.png
pystrat/swatches/623.png
pystrat/swatches/624.png
pystrat/swatches/625.png
pystrat/swatches/626.png
pystrat/swatches/627.png
pystrat/swatches/628.png
pystrat/swatches/629.png
pystrat/swatches/630.png
pystrat/swatches/631.png
pystrat/swatches/632.png
pystrat/swatches/633.png
pystrat/swatches/634.png
pystrat/swatches/635.png
pystrat/swatches/636.png
pystrat/swatches/637.png
pystrat/swatches/638.png
pystrat/swatches/639.png
pystrat/swatches/640.png
pystrat/swatches/641.png
pystrat/swatches/642.png
pystrat/swatches/643.png
pystrat/swatches/644.png
pystrat/swatches/645.png
pystrat/swatches/646.png
pystrat/swatches/647.png
pystrat/swatches/648.png
pystrat/swatches/649.png
pystrat/swatches/650.png
pystrat/swatches/651.png
pystrat/swatches/652.png
pystrat/swatches/653.png
pystrat/swatches/654.png
pystrat/swatches/655.png
pystrat/swatches/656.png
pystrat/swatches/657.png
pystrat-2.3.0.dist-info/licenses/LICENSE.txt
pystrat-2.3.0.dist-info/METADATA
pystrat-2.3.0.dist-info/WHEEL
pystrat-2.3.0.dist-info/top_level.txt
pystrat-2.3.0.dist-info/RECORD
