Metadata-Version: 2.4
Name: pystrat
Version: 2.3.0
Summary: Stratigraphic plotting tools for Python
Home-page: https://github.com/yuempark/pystrat
Author: [Adrian Tasistro-Hart, Yuem Park]
Author-email: [adrian@tasistro-hart.com, yuempark@gmail.com]
License: GPL-3.0-only
Project-URL: Documentation, https://pystrat.readthedocs.io/en/latest/
Project-URL: Source, https://github.com/yuempark/pystrat
Project-URL: Changelog, https://pystrat.readthedocs.io/en/latest/changelog.html
Platform: any
Classifier: Development Status :: 5 - Production/Stable
Classifier: Programming Language :: Python
License-File: LICENSE.txt
Requires-Dist: importlib-metadata; python_version < "3.8"
Requires-Dist: numpy
Requires-Dist: pandas
Requires-Dist: matplotlib
Requires-Dist: pillow
Provides-Extra: testing
Requires-Dist: setuptools; extra == "testing"
Requires-Dist: pytest; extra == "testing"
Requires-Dist: pytest-cov; extra == "testing"
Dynamic: license-file
